systrack/__init__.py
systrack/__main__.py
systrack/elf.py
systrack/kconfig.py
systrack/kconfig_options.py
systrack/kernel.py
systrack/location.py
systrack/log.py
systrack/output.py
systrack/signature.py
systrack/syscall.py
systrack/type_hints.py
systrack/utils.py
systrack/version.py
systrack/arch/__init__.py
systrack/arch/arch_base.py
systrack/arch/arm.py
systrack/arch/arm64.py
systrack/arch/mips.py
systrack/arch/powerpc.py
systrack/arch/riscv.py
systrack/arch/s390.py
systrack/arch/x86.py
systrack/templates/syscall_table.css
systrack/templates/syscall_table.html
systrack/templates/syscall_table.js
systrack-0.8.dist-info/METADATA
systrack-0.8.dist-info/WHEEL
systrack-0.8.dist-info/entry_points.txt
systrack-0.8.dist-info/licenses/LICENSE
systrack-0.8.dist-info/RECORD
