Metadata-Version: 2.4
Name: systrack
Version: 0.8
Summary: Linux kernel syscall implementation tracker
Project-URL: Homepage, https://github.com/mebeim/systrack
Project-URL: Repository, https://github.com/mebeim/systrack.git
Project-URL: Changelog, https://github.com/mebeim/systrack/blob/master/CHANGELOG.md
Author: Marco Bonelli
Author-email: Marco Bonelli <marco@mebeim.net>
Maintainer: Marco Bonelli
Maintainer-email: Marco Bonelli <marco@mebeim.net>
License: GNU General Public License v3 (GPLv3)
License-File: LICENSE
Keywords: abi,elf,kconfig,kernel,linux,syscall,systrack
Classifier: Development Status :: 4 - Beta
Classifier: Environment :: Console
Classifier: Intended Audience :: Developers
Classifier: Intended Audience :: Science/Research
Classifier: Intended Audience :: System Administrators
Classifier: License :: OSI Approved :: GNU General Public License v3 (GPLv3)
Classifier: Natural Language :: English
Classifier: Operating System :: OS Independent
Classifier: Programming Language :: Python :: 3
Classifier: Topic :: Security
Classifier: Topic :: Software Development :: Embedded Systems
Classifier: Topic :: Software Development :: Testing
Classifier: Topic :: System :: Operating System Kernels :: Linux
Classifier: Topic :: Utilities
Requires-Python: >=3.8
Requires-Dist: iced-x86~=1.21.0
Requires-Dist: jinja2~=3.1.2
